synapso_cli/__init__.py
synapso_cli/core.py
synapso_cli/main.py
synapso_cli-0.3.0.dist-info/licenses/LICENSE
synapso_cli-0.3.0.dist-info/METADATA
synapso_cli-0.3.0.dist-info/WHEEL
synapso_cli-0.3.0.dist-info/entry_points.txt
synapso_cli-0.3.0.dist-info/top_level.txt
synapso_cli-0.3.0.dist-info/RECORD
