Metadata-Version: 2.4
Name: synapso_cli
Version: 0.3.0
Summary: Internal
Author: Ganesh Palanikumar
Requires-Python: >=3.13
License-File: LICENSE
Requires-Dist: typer==0.16.0
Requires-Dist: synapso-core>=0.2.0
Requires-Dist: pyyaml==6.0.2
Dynamic: license-file
